ftrixminer_api/__init__.py
ftrixminer_api/aiohttp_client.py
ftrixminer_api/context_base.py
ftrixminer_api/exceptions.py
ftrixminer_api/thing.py
ftrixminer_api/things.py
ftrixminer_api/miners/__init__.py
ftrixminer_api/miners/aiohttp.py
ftrixminer_api/miners/constants.py
ftrixminer_api/miners/context.py
ftrixminer_api/miners/miners.py
ftrixminer_cli/__init__.py
ftrixminer_cli/main.py
ftrixminer_cli/version.py
ftrixminer_cli/subcommands/__init__.py
ftrixminer_cli/subcommands/base.py
ftrixminer_cli/subcommands/explore1.py
ftrixminer_cli/subcommands/service.py
ftrixminer_lib/__init__.py
ftrixminer_lib/__main__.py
ftrixminer_lib/_version.py
ftrixminer_lib/base_aiohttp.py
ftrixminer_lib/envvar.py
ftrixminer_lib/exceptions.py
ftrixminer_lib/version.py
ftrixminer_lib/contexts/__init__.py
ftrixminer_lib/contexts/base.py
ftrixminer_lib/miners/__init__.py
ftrixminer_lib/miners/aiohttp.py
ftrixminer_lib/miners/base.py
ftrixminer_lib/miners/constants.py
ftrixminer_lib/miners/context.py
ftrixminer_lib/miners/direct_poll.py
ftrixminer_lib/miners/miners.py
ftrixminer-1.3.2.dist-info/LICENSE
ftrixminer-1.3.2.dist-info/METADATA
ftrixminer-1.3.2.dist-info/WHEEL
ftrixminer-1.3.2.dist-info/entry_points.txt
ftrixminer-1.3.2.dist-info/top_level.txt
ftrixminer-1.3.2.dist-info/RECORD
